<annotation>
	<folder>labelImgData</folder>
	<filename>01df013e44a31995a4ef4777a8afa773.jpg</filename>
	<path>D:\Eye\train_jpg\labelImgData\01df013e44a31995a4ef4777a8afa773.jpg</path>
	<source>
		<database>Unknown</database>
	</source>
	<size>
		<width>1440</width>
		<height>1080</height>
		<depth>3</depth>
	</size>
	<segmented>0</segmented>
	<object>
		<name>Optic-Disc</name>
		<pose>Unspecified</pose>
		<truncated>0</truncated>
		<difficult>0</difficult>
		<bndbox>
			<xmin>185</xmin>
			<ymin>384</ymin>
			<xmax>353</xmax>
			<ymax>570</ymax>
		</bndbox>
	</object>
	<object>
		<name>Venules</name>
		<pose>Unspecified</pose>
		<truncated>0</truncated>
		<difficult>0</difficult>
		<bndbox>
			<xmin>345</xmin>
			<ymin>131</ymin>
			<xmax>1044</xmax>
			<ymax>275</ymax>
		</bndbox>
	</object>
	<object>
		<name>Hemorrhages</name>
		<pose>Unspecified</pose>
		<truncated>0</truncated>
		<difficult>0</difficult>
		<bndbox>
			<xmin>571</xmin>
			<ymin>449</ymin>
			<xmax>760</xmax>
			<ymax>662</ymax>
		</bndbox>
	</object>
	<object>
		<name>Venules</name>
		<pose>Unspecified</pose>
		<truncated>0</truncated>
		<difficult>0</difficult>
		<bndbox>
			<xmin>305</xmin>
			<ymin>610</ymin>
			<xmax>1113</xmax>
			<ymax>913</ymax>
		</bndbox>
	</object>
	<object>
		<name>Microaneurysms</name>
		<pose>Unspecified</pose>
		<truncated>0</truncated>
		<difficult>0</difficult>
		<bndbox>
			<xmin>979</xmin>
			<ymin>422</ymin>
			<xmax>1106</xmax>
			<ymax>560</ymax>
		</bndbox>
	</object>
</annotation>
